<?xml version="1.0" encoding="utf-8"?>
<translation xmlns:xsd="http://www.w3.org/2001/XMLSchema" xmlns:xsi="http://www.w3.org/2001/XMLSchema-instance" lang="pl">
  <phrase k="Back" v="powrót" />
  <phrase k="Bib" v="plastron" />
  <phrase k="Calendar" v="kalendarz" />
  <phrase k="Calendar editor" v="edytor kalendarza" />
  <phrase k="Calendars" v="kalendarze" />
  <phrase k="Classifications" v="klasyfikacje" />
  <phrase k="Country code" v="kod kraju" />
  <phrase k="Credits" v="autorzy" />
  <phrase k="Customise" v="dostosuj" />
  <phrase k="Edit" v="edytuj" />
  <phrase k="Equipment" v="sprzęt" />
  <phrase k="Events" v="konkursy" />
  <phrase k="Exit" v="wyjście" />
  <phrase k="First name" v="imię" />
  <phrase k="Full screen" v="pełny ekran" />
  <phrase k="Gates count" v="liczba belek" />
  <phrase k="Gate stairs left" v="schody belka lewe" />
  <phrase k="Gate stairs right" v="schody belka prawe" />
  <phrase k="Gender" v="płeć" />
  <phrase k="Helmet" v="kask" />
  <phrase k="Help" v="pomoc" />
  <phrase k="#HelpText" v="Start - lewy przycisk myszy\nWybicie - lewy przycisk myszy\nSterowanie w locie - ruch myszą góra-dół\nLądowanie z telemarkiem - lewy przycisk myszy\nLądowanie bez telemarku - oba przyciski myszy\nZmiana kamery - klawisze F1 - F5\nOdbicie lustrzane kamery - klawisz Q\n\nAutor zdjęcia w menu głównym: Mateusz Stóf" />
  <phrase k="Hill" v="skocznia" />
  <phrase k="Hills" v="skocznie" />
  <phrase k="Hill surface" v="nawierzchnia skoczni" />
  <phrase k="Image" v="zdjęcie" />
  <phrase k="Individual events" v="konkursy indywidualne" />
  <phrase k="In limit" v="limit wejścia" />
  <phrase k="Inrun stairs left" v="schody najazd lewe" />
  <phrase k="Inrun stairs right" v="schody najazd prawe" />
  <phrase k="Jumpers" v="skoczkowie" />
  <phrase k="Language" v="język" />
  <phrase k="Last name" v="nazwisko" />
  <phrase k="Limit" v="limit" />
  <phrase k="Main menu" v="menu główne" />
  <phrase k="Medal places" v="miejsca medalowe" />
  <phrase k="Mouse sensitivity" v="czułość myszy" />
  <phrase k="Name" v="nazwa" />
  <phrase k="Next event" v="następny konkurs" />
  <phrase k="Next event info" v="informacje o następnym konkurs" />
  <phrase k="Next jumper" v="następny skoczek" />
  <phrase k="No" v="nie" />
  <phrase k="Play" v="graj" />
  <phrase k="Points table individual" v="tabela punktowa indywidualne" />
  <phrase k="Points table team" v="tabela punktowa drużynowe" />
  <phrase k="Pre-qualification ranking" v="ranking pre-kwalifikacyjny" />
  <phrase k="Preset" v="preset" />
  <phrase k="Presets" v="presety" />
  <phrase k="Profile type" v="rodzaj profilu" />
  <phrase k="Qualification ranking" v="ranking kwalifikacyjny" />
  <phrase k="Quality" v="jakość" />
  <phrase k="Resolution" v="rozdzielczość" />
  <phrase k="Results" v="wyniki" />
  <phrase k="Resume" v="wznów" />
  <phrase k="Saves" v="zapisy gry" />
  <phrase k="Settings" v="ustawienia" />
  <phrase k="Skin" v="skóra" />
  <phrase k="Skis" v="narty" />
  <phrase k="Start order ranking" v="ranking kolejności startowej" />
  <phrase k="Suit bottom back" v="kombinezon dół tył" />
  <phrase k="Suit bottom front" v="Kombinezon dół przód" />
  <phrase k="Suit top back" v="kombinezon góra tył" />
  <phrase k="Suit top front" v="kombinezon góra przód" />
  <phrase k="Terrain steepness" v="nachylenie terenu" />
  <phrase k="Training" v="trening" />
  <phrase k="Type" v="rodzaj" />
  <phrase k="Yes" v="tak" />
</translation>