[{"name":"2017/2018","competitorsIds":["AUT-M-Moerth-Claudio#0","AUT-M-Leitner-Clemens#0","AUT-M-Hoerl-Jan#0","AUT-M-Aschenwald-Philipp#0","AUT-M-Wohlgenannt-Ulrich#0","AUT-M-Huber-Stefan#0","AUT-M-Kraft-Stefan#0","AUT-M-Aigner-Clemens#0","AUT-M-Huber-Daniel#0","AUT-M-Schiffner-Markus#0","AUT-M-Hayboeck-Michael#0","AUT-M-Schlierenzauer-Gregor#0","AUT-M-Fettner-Manuel#0","AUT-F-Kramer-Marita#0","BUL-M-Zografski-Vladimir#0","CAN-M-Boyd-clowes-Mackenzie#0","CZE-M-Vancura-Tomas#0","CZE-M-Stursa-Vojtech#0","CZE-M-Kozisek-Cestmir#0","CZE-M-Koudelka-Roman#0","CZE-M-Hlava-Lukas#0","EST-M-Aigro-Artti#0","FIN-M-Kytosaho-Niko#0","FIN-M-Alamommo-Andreas#0","FIN-M-Nousiainen-Eetu#0","FIN-M-Aalto-Antti#0","FIN-M-Maatta-Jarkko#0","FRA-M-Learoyd-Jonathan#0","GER-M-Schmid-Constantin#0","GER-M-Baer-Moritz#0","GER-M-Siegel-David#0","GER-M-Wellinger-Andreas#0","GER-M-Geiger-Karl#0","GER-M-Leyhe-Stephan#0","GER-M-Freitag-Richard#0","GER-M-Eisenbichler-Markus#0","GER-M-Paschke-Pius#0","GER-M-Freund-Severin#0","ITA-M-Insam-Alex#0","JPN-M-Iwasa-Yuken#0","JPN-M-Sato-Keiichi#0","JPN-M-Kobayashi-Ryoyu#0","JPN-M-Nakamura-Naoki#0","JPN-M-Sato-Yukiya#0","JPN-M-Kobayashi-Junshiro#0","JPN-M-Tochimoto-Shohei#0","JPN-M-Takeuchi-Taku#0","JPN-M-Ito-Daiki#0","JPN-M-Kasai-Noriaki#0","KAZ-M-Tkachenko-Sergey#0","KOR-M-Choi-Seou#0","KOR-M-Choi-Heung_Chul#0","NOR-M-Markeng-Thomas_Aasen#0","NOR-M-Lindvik-Marius#0","NOR-M-Pedersen-Robin#0","NOR-M-Buskum-Andreas_Granerud#0","NOR-M-Granerud-Halvor_Egner#0","NOR-M-Forfang-Johann_Andre#0","NOR-M-Tande-Daniel_Andre#0","NOR-M-Aune-Joakim#0","NOR-M-Fannemel-Anders#0","NOR-M-Johansson-Robert#0","NOR-F-Lundby-Maren#0","POL-M-Niznik-Adam#0","POL-M-Juroszek-Kacper#0","POL-M-Pilch-Tomasz#0","POL-M-Krzak-Jaroslaw#0","POL-M-Wasek-Pawel#0","POL-M-Stekala-Andrzej#0","POL-M-Wolny-Jakub#0","POL-M-Muranka-Klemens#0","POL-M-Zniszczol-Aleksander#0","POL-M-Kot-Maciej#0","POL-M-Kubacki-Dawid#0","POL-M-Stoch-Kamil#0","POL-M-Zyla-Piotr#0","POL-M-Hula-Stefan#0","RUS-M-Nazarov-Mikhail#0","RUS-M-Klimov-Evgeniy#0","RUS-M-Trofimov-Roman_Sergeevich#0","RUS-M-Vassiliev-Dmitriy#0","SLO-M-Mogel-Zak#0","SLO-M-Zajc-Timi#0","SLO-M-Prevc-Domen#0","SLO-M-Pavlovcic-Bor#0","SLO-M-Jelar-Ziga#0","SLO-M-Bartol-Tilen#0","SLO-M-Lanisek-Anze#0","SLO-M-Semenic-Anze#0","SLO-M-Prevc-Peter#0","SLO-M-Tepes-Jurij#0","SLO-M-Damjan-Jernej#0","SUI-M-Peter-Dominik#0","SUI-M-Schuler-Andreas#0","SUI-M-Peier-Killian#0","SUI-M-Deschwanden-Gregor#0","SUI-M-Ammann-Simon#0","USA-M-Larson-Casey#0","USA-M-Bickner-Kevin#0"],"teams":[{"teamName":"Austria","countryCode":"AUT","competitorsIds":["AUT-M-Moerth-Claudio#0","AUT-M-Leitner-Clemens#0","AUT-M-Hoerl-Jan#0","AUT-M-Aschenwald-Philipp#0","AUT-M-Wohlgenannt-Ulrich#0","AUT-M-Huber-Stefan#0","AUT-M-Kraft-Stefan#0","AUT-M-Aigner-Clemens#0","AUT-M-Huber-Daniel#0","AUT-M-Schiffner-Markus#0","AUT-M-Hayboeck-Michael#0","AUT-M-Schlierenzauer-Gregor#0","AUT-M-Fettner-Manuel#0","AUT-F-Kramer-Marita#0"]},{"teamName":"Bulgaria","countryCode":"BUL","competitorsIds":["BUL-M-Zografski-Vladimir#0"]},{"teamName":"Canada","countryCode":"CAN","competitorsIds":["CAN-M-Boyd-clowes-Mackenzie#0"]},{"teamName":"Czech Republic","countryCode":"CZE","competitorsIds":["CZE-M-Vancura-Tomas#0","CZE-M-Stursa-Vojtech#0","CZE-M-Kozisek-Cestmir#0","CZE-M-Koudelka-Roman#0","CZE-M-Hlava-Lukas#0"]},{"teamName":"Estonia","countryCode":"EST","competitorsIds":["EST-M-Aigro-Artti#0"]},{"teamName":"Finland","countryCode":"FIN","competitorsIds":["FIN-M-Kytosaho-Niko#0","FIN-M-Alamommo-Andreas#0","FIN-M-Nousiainen-Eetu#0","FIN-M-Aalto-Antti#0","FIN-M-Maatta-Jarkko#0"]},{"teamName":"France","countryCode":"FRA","competitorsIds":["FRA-M-Learoyd-Jonathan#0"]},{"teamName":"Germany","countryCode":"GER","competitorsIds":["GER-M-Schmid-Constantin#0","GER-M-Baer-Moritz#0","GER-M-Siegel-David#0","GER-M-Wellinger-Andreas#0","GER-M-Geiger-Karl#0","GER-M-Leyhe-Stephan#0","GER-M-Freitag-Richard#0","GER-M-Eisenbichler-Markus#0","GER-M-Paschke-Pius#0","GER-M-Freund-Severin#0"]},{"teamName":"Italy","countryCode":"ITA","competitorsIds":["ITA-M-Insam-Alex#0"]},{"teamName":"Japan","countryCode":"JPN","competitorsIds":["JPN-M-Iwasa-Yuken#0","JPN-M-Sato-Keiichi#0","JPN-M-Kobayashi-Ryoyu#0","JPN-M-Nakamura-Naoki#0","JPN-M-Sato-Yukiya#0","JPN-M-Kobayashi-Junshiro#0","JPN-M-Tochimoto-Shohei#0","JPN-M-Takeuchi-Taku#0","JPN-M-Ito-Daiki#0","JPN-M-Kasai-Noriaki#0"]},{"teamName":"Kazakhstan","countryCode":"KAZ","competitorsIds":["KAZ-M-Tkachenko-Sergey#0"]},{"teamName":"Korea, Republic Of","countryCode":"KOR","competitorsIds":["KOR-M-Choi-Seou#0","KOR-M-Choi-Heung_Chul#0"]},{"teamName":"Norway","countryCode":"NOR","competitorsIds":["NOR-M-Markeng-Thomas_Aasen#0","NOR-M-Lindvik-Marius#0","NOR-M-Pedersen-Robin#0","NOR-M-Buskum-Andreas_Granerud#0","NOR-M-Granerud-Halvor_Egner#0","NOR-M-Forfang-Johann_Andre#0","NOR-M-Tande-Daniel_Andre#0","NOR-M-Aune-Joakim#0","NOR-M-Fannemel-Anders#0","NOR-M-Johansson-Robert#0","NOR-F-Lundby-Maren#0"]},{"teamName":"Poland","countryCode":"POL","competitorsIds":["POL-M-Niznik-Adam#0","POL-M-Juroszek-Kacper#0","POL-M-Pilch-Tomasz#0","POL-M-Krzak-Jaroslaw#0","POL-M-Wasek-Pawel#0","POL-M-Stekala-Andrzej#0","POL-M-Wolny-Jakub#0","POL-M-Muranka-Klemens#0","POL-M-Zniszczol-Aleksander#0","POL-M-Kot-Maciej#0","POL-M-Kubacki-Dawid#0","POL-M-Stoch-Kamil#0","POL-M-Zyla-Piotr#0","POL-M-Hula-Stefan#0"]},{"teamName":"Russian Federation","countryCode":"RUS","competitorsIds":["RUS-M-Nazarov-Mikhail#0","RUS-M-Klimov-Evgeniy#0","RUS-M-Trofimov-Roman_Sergeevich#0","RUS-M-Vassiliev-Dmitriy#0"]},{"teamName":"Slovenia","countryCode":"SLO","competitorsIds":["SLO-M-Mogel-Zak#0","SLO-M-Zajc-Timi#0","SLO-M-Prevc-Domen#0","SLO-M-Pavlovcic-Bor#0","SLO-M-Jelar-Ziga#0","SLO-M-Bartol-Tilen#0","SLO-M-Lanisek-Anze#0","SLO-M-Semenic-Anze#0","SLO-M-Prevc-Peter#0","SLO-M-Tepes-Jurij#0","SLO-M-Damjan-Jernej#0"]},{"teamName":"Switzerland","countryCode":"SUI","competitorsIds":["SUI-M-Peter-Dominik#0","SUI-M-Schuler-Andreas#0","SUI-M-Peier-Killian#0","SUI-M-Deschwanden-Gregor#0","SUI-M-Ammann-Simon#0"]},{"teamName":"United States","countryCode":"USA","competitorsIds":["USA-M-Larson-Casey#0","USA-M-Bickner-Kevin#0"]}],"classifications":[{"name":"World Cup","eventType":"Individual","classificationType":"Place","teamClassificationLimitType":0,"teamCompetitorsLimit":0,"medalPlaces":0,"events":[],"pointsTables":[{"name":"","value":[100,80,60,50,45,40,36,32,29,26,24,22,20,18,16,15,14,13,12,11,10,9,8,7,6,5,4,3,2,1]}],"leaderBibColor":"ffff00"},{"name":"Nations Cup","eventType":"Team","classificationType":"Place","teamClassificationLimitType":0,"teamCompetitorsLimit":0,"medalPlaces":0,"events":[],"pointsTables":[{"name":"","value":[100,80,60,50,45,40,36,32,29,26,24,22,20,18,16,15,14,13,12,11,10,9,8,7,6,5,4,3,2,1]},{"name":"","value":[400,350,300,250,200,150,100,50]}],"leaderBibColor":"ffff00"}],"events":[{"classifications":[],"eventType":"Individual","hillId":"Wisla HS134","hillSurface":"Snow","id":0,"roundInfos":{"name":"Individual2Rounds","roundInfos":[{"roundType":"Normal","outLimitType":"Normal","outLimit":30,"useOrdRank":[false,false,false,false,false,false,false,false,false,false,false,false,false,false,false,false,false,false,false,false,false,false,false,false,false,false,false,false,false,false,false,false,false,false,false,false,false,false,false,false,false,false,false,false,false,false,false,false,false,false,false,false],"disableJudgesMarks":false,"has95Rule":true,"reversedBibs":false,"reassignBibs":false,"gateCompensation":true,"windCompensation":true},{"roundType":"Normal","outLimitType":"None","outLimit":-1,"useOrdRank":[false,false,false,false,false,false,false,false,false,false,false,false,false,false,false,false,false,false,false,false,false,false,false,false,false,false,false,false,false,false,false,false,false,false,false,false,false,false,false,false,false,false,false,false,false,false,false,false,false,false,false,false],"disableJudgesMarks":false,"has95Rule":true,"reversedBibs":false,"reassignBibs":false,"gateCompensation":true,"windCompensation":true}]},"ordRankType":"Classification","ordRankId":0,"qualRankType":"None","qualRankId":0,"inLimitType":"None","inLimit":0,"preQualRankType":"None","preQualRankId":0,"preQualLimitType":"None","preQualLimit":0},{"classifications":[],"eventType":"Team","hillId":"Wisla HS134","hillSurface":"Snow","id":1,"roundInfos":{"name":"","roundInfos":[{"roundType":"Normal","outLimitType":"Normal","outLimit":8,"useOrdRank":[false,false,false,false,false,false,false,false,false,false,false,false,false,false,false,false,false,false,false,false,false,false,false,false,false,false,false,false,false,false,false,false,false,false,false,false,false,false,false,false,false,false,false,false,false,false,false,false,false,false,false,false,true,true,true,true],"disableJudgesMarks":false,"has95Rule":false,"reversedBibs":false,"reassignBibs":false,"gateCompensation":true,"windCompensation":true},{"roundType":"Normal","outLimitType":"None","outLimit":0,"useOrdRank":[false,false,false,false,false,false,false,false,false,false,false,false,false,false,false,false,false,false,false,false,false,false,false,false,false,false,false,false,false,false,false,false,false,false,false,false,false,false,false,false,false,false,false,false,false,false,false,false,false,false,false,false,true,true,true,false],"disableJudgesMarks":false,"has95Rule":false,"reversedBibs":false,"reassignBibs":false,"gateCompensation":true,"windCompensation":true}]},"ordRankType":"Classification","ordRankId":2,"qualRankType":"None","qualRankId":0,"inLimitType":"None","inLimit":0,"preQualRankType":"None","preQualRankId":0,"preQualLimitType":"None","preQualLimit":0},{"classifications":[0],"eventType":"Individual","hillId":"Wisla HS134","hillSurface":"Snow","id":2,"roundInfos":{"name":"","roundInfos":[]},"ordRankType":"Classification","ordRankId":0,"qualRankType":"Event","qualRankId":0,"inLimitType":"None","inLimit":0,"preQualRankType":"None","preQualRankId":0,"preQualLimitType":"None","preQualLimit":0},{"classifications":[],"eventType":"Individual","hillId":"Kuusamo HS142","hillSurface":"Snow","id":3,"roundInfos":{"name":"","roundInfos":[]},"ordRankType":"Classification","ordRankId":0,"qualRankType":"None","qualRankId":0,"inLimitType":"None","inLimit":0,"preQualRankType":"None","preQualRankId":0,"preQualLimitType":"None","preQualLimit":0},{"classifications":[0],"eventType":"Individual","hillId":"Kuusamo HS142","hillSurface":"Snow","id":4,"roundInfos":{"name":"","roundInfos":[]},"ordRankType":"Classification","ordRankId":0,"qualRankType":"Event","qualRankId":3,"inLimitType":"None","inLimit":0,"preQualRankType":"None","preQualRankId":0,"preQualLimitType":"None","preQualLimit":0}]},{"name":"2018/2019","competitorsIds":["AUT-M-Kraft-Stefan#0","GER-M-Geiger-Karl#0","NOR-M-Forfang-Johann_Andre#0","POL-M-Kubacki-Dawid#0","POL-M-Stoch-Kamil#0","SLO-M-Prevc-Peter#0","NOR-M-Tande-Daniel_Andre#0","AUT-M-Aschenwald-Philipp#0","AUT-M-Hayboeck-Michael#0","AUT-M-Schlierenzauer-Gregor#0","AUT-M-Huber-Daniel#0","GER-M-Leyhe-Stephan#0","GER-M-Eisenbichler-Markus#0","GER-M-Freitag-Richard#0","GER-M-Paschke-Pius#0","NOR-M-Lindvik-Marius#0","NOR-M-Johansson-Robert#0","POL-M-Zyla-Piotr#0","POL-M-Wolny-Jakub#0","POL-M-Kot-Maciej#0"],"teams":[{"teamName":"Austria","countryCode":"AUT","competitorsIds":["AUT-M-Kraft-Stefan#0","AUT-M-Aschenwald-Philipp#0","AUT-M-Hayboeck-Michael#0","AUT-M-Schlierenzauer-Gregor#0","AUT-M-Huber-Daniel#0"]},{"teamName":"Germany","countryCode":"GER","competitorsIds":["GER-M-Geiger-Karl#0","GER-M-Leyhe-Stephan#0","GER-M-Eisenbichler-Markus#0","GER-M-Freitag-Richard#0","GER-M-Paschke-Pius#0"]},{"teamName":"Norway","countryCode":"NOR","competitorsIds":["NOR-M-Forfang-Johann_Andre#0","NOR-M-Tande-Daniel_Andre#0","NOR-M-Lindvik-Marius#0","NOR-M-Johansson-Robert#0"]},{"teamName":"Poland","countryCode":"POL","competitorsIds":["POL-M-Kubacki-Dawid#0","POL-M-Stoch-Kamil#0","POL-M-Zyla-Piotr#0","POL-M-Wolny-Jakub#0","POL-M-Kot-Maciej#0"]},{"teamName":"Slovenia","countryCode":"SLO","competitorsIds":["SLO-M-Prevc-Peter#0"]}],"classifications":[{"name":"World Cup","eventType":"Individual","classificationType":"Place","teamClassificationLimitType":0,"teamCompetitorsLimit":0,"medalPlaces":0,"events":[],"pointsTables":[{"name":"Individual","value":[100,80,60,50,45,40,36,32,29,26,24,22,20,18,16,15,14,13,12,11,10,9,8,7,6,5,4,3,2,1]}],"leaderBibColor":"ffff00"},{"name":"Nations Cup","eventType":"Team","classificationType":"Place","teamClassificationLimitType":0,"teamCompetitorsLimit":0,"medalPlaces":0,"events":[],"pointsTables":[{"name":"Individual","value":[100,80,60,50,45,40,36,32,29,26,24,22,20,18,16,15,14,13,12,11,10,9,8,7,6,5,4,3,2,1]},{"name":"Team","value":[400,350,300,250,200,150,100,50]}],"leaderBibColor":"ffbb00"}],"events":[{"classifications":[],"eventType":"Individual","hillId":"Wisla HS134","hillSurface":"Snow","id":0,"roundInfos":{"name":"Qualification","roundInfos":[{"roundType":"Normal","outLimitType":"Normal","outLimit":50,"useOrdRank":[false,false,false,false,false,false,false,false,false,false,false,false,false,false,false,false,false,false,false,false,false,false,false,false,false,false,false,false,false,false,false,false,false,false,false,false,false,false,false,false,false,false,false,false,false,false,false,false],"disableJudgesMarks":false,"has95Rule":true,"reversedBibs":false,"reassignBibs":false,"gateCompensation":true,"windCompensation":true}]},"ordRankType":"Classification","ordRankId":0,"qualRankType":"None","qualRankId":0,"inLimitType":"None","inLimit":0,"preQualRankType":"None","preQualRankId":0,"preQualLimitType":"None","preQualLimit":0},{"classifications":[1],"eventType":"Team","hillId":"Wisla HS134","hillSurface":"Snow","id":1,"roundInfos":{"name":"Team2Rounds","roundInfos":[{"roundType":"Normal","outLimitType":"Normal","outLimit":30,"useOrdRank":[false,false,false,false,false,false,false,false,false,false,false,false,false,false,false,false,false,false,false,false,false,false,false,false,false,false,false,false,false,false,false,false,true,true,true,true],"disableJudgesMarks":false,"has95Rule":true,"reversedBibs":false,"reassignBibs":false,"gateCompensation":true,"windCompensation":true},{"roundType":"Normal","outLimitType":"Normal","outLimit":8,"useOrdRank":[false,false,false,false,false,false,false,false,false,false,false,false,false,false,false,false,false,false,false,false,false,false,false,false,false,false,false,false,false,false,false,false,true,true,true,false],"disableJudgesMarks":false,"has95Rule":true,"reversedBibs":false,"reassignBibs":false,"gateCompensation":true,"windCompensation":true}]},"ordRankType":"Classification","ordRankId":1,"qualRankType":"None","qualRankId":0,"inLimitType":"None","inLimit":0,"preQualRankType":"None","preQualRankId":0,"preQualLimitType":"None","preQualLimit":0},{"classifications":[0],"eventType":"Individual","hillId":"Wisla HS134","hillSurface":"Snow","id":2,"roundInfos":{"name":"Individual2Rounds","roundInfos":[{"roundType":"Normal","outLimitType":"Normal","outLimit":30,"useOrdRank":[false,false,false,false,false,false,false,false,false,false,false,false,false,false,false,false,false,false,false,false,false,false,false,false,false,false,false,false,false,false,false,false,false,false,false,false,false,false,false,false,false,false,false,false],"disableJudgesMarks":false,"has95Rule":true,"reversedBibs":false,"reassignBibs":false,"gateCompensation":true,"windCompensation":true},{"roundType":"Normal","outLimitType":"None","outLimit":-1,"useOrdRank":[false,false,false,false,false,false,false,false,false,false,false,false,false,false,false,false,false,false,false,false,false,false,false,false,false,false,false,false,false,false,false,false,false,false,false,false,false,false,false,false,false,false,false,false],"disableJudgesMarks":false,"has95Rule":true,"reversedBibs":false,"reassignBibs":false,"gateCompensation":true,"windCompensation":true}]},"ordRankType":"Classification","ordRankId":0,"qualRankType":"Event","qualRankId":0,"inLimitType":"None","inLimit":0,"preQualRankType":"None","preQualRankId":0,"preQualLimitType":"None","preQualLimit":0},{"classifications":[],"eventType":"Individual","hillId":"Kuusamo HS142","hillSurface":"Snow","id":3,"roundInfos":{"name":"Qualification","roundInfos":[{"roundType":"Normal","outLimitType":"Normal","outLimit":50,"useOrdRank":[false,false,false,false,false,false,false,false,false,false,false,false,false,false,false,false,false,false,false,false,false,false,false,false,false,false,false,false,false,false,false,false,false,false,false,false,false,false,false,false,false,false,false,false,false,false,false,false],"disableJudgesMarks":false,"has95Rule":true,"reversedBibs":false,"reassignBibs":false,"gateCompensation":true,"windCompensation":true}]},"ordRankType":"Classification","ordRankId":0,"qualRankType":"None","qualRankId":0,"inLimitType":"None","inLimit":0,"preQualRankType":"None","preQualRankId":0,"preQualLimitType":"None","preQualLimit":0},{"classifications":[0],"eventType":"Individual","hillId":"Kuusamo HS142","hillSurface":"Snow","id":4,"roundInfos":{"name":"Individual2Rounds","roundInfos":[{"roundType":"Normal","outLimitType":"Normal","outLimit":30,"useOrdRank":[false,false,false,false,false,false,false,false,false,false,false,false,false,false,false,false,false,false,false,false,false,false,false,false,false,false,false,false,false,false,false,false,false,false,false,false,false,false,false,false,false,false,false,false,false,false,false,false],"disableJudgesMarks":false,"has95Rule":true,"reversedBibs":false,"reassignBibs":false,"gateCompensation":true,"windCompensation":true},{"roundType":"Normal","outLimitType":"None","outLimit":-1,"useOrdRank":[false,false,false,false,false,false,false,false,false,false,false,false,false,false,false,false,false,false,false,false,false,false,false,false,false,false,false,false,false,false,false,false,false,false,false,false,false,false,false,false,false,false,false,false,false,false,false,false],"disableJudgesMarks":false,"has95Rule":true,"reversedBibs":false,"reassignBibs":false,"gateCompensation":true,"windCompensation":true}]},"ordRankType":"Classification","ordRankId":0,"qualRankType":"Event","qualRankId":3,"inLimitType":"None","inLimit":0,"preQualRankType":"None","preQualRankId":0,"preQualLimitType":"None","preQualLimit":0}]},{"name":"2019/2020","competitorsIds":["AUT-M-Moerth-Claudio#0","AUT-M-Leitner-Clemens#0","AUT-M-Hoerl-Jan#0","AUT-M-Aschenwald-Philipp#0","AUT-M-Wohlgenannt-Ulrich#0","AUT-M-Huber-Stefan#0","AUT-M-Kraft-Stefan#0","AUT-M-Aigner-Clemens#0","AUT-M-Huber-Daniel#0","AUT-M-Schiffner-Markus#0","AUT-M-Hayboeck-Michael#0","AUT-M-Schlierenzauer-Gregor#0","AUT-M-Fettner-Manuel#0","AUT-F-Kramer-Marita#0","AUT-F-Hoelzl-Chiara#0","AUT-F-Sorschag-Sophie#0","BUL-M-Zografski-Vladimir#0","CAN-M-Boyd-clowes-Mackenzie#0","CZE-M-Polasek-Viktor#0","CZE-M-Vancura-Tomas#0","CZE-M-Stursa-Vojtech#0","CZE-M-Kozisek-Cestmir#0","CZE-M-Koudelka-Roman#0","CZE-M-Hlava-Lukas#0","EST-M-Aigro-Artti#0","FIN-M-Kytosaho-Niko#0","FIN-M-Alamommo-Andreas#0","FIN-M-Nousiainen-Eetu#0","FIN-M-Aalto-Antti#0","FIN-M-Maatta-Jarkko#0","FRA-M-Learoyd-Jonathan#0","FRA-F-Pagnier-Josephine#0","GER-M-Schmid-Constantin#0","GER-M-Baer-Moritz#0","GER-M-Siegel-David#0","GER-M-Wellinger-Andreas#0","GER-M-Geiger-Karl#0","GER-M-Leyhe-Stephan#0","GER-M-Freitag-Richard#0","GER-M-Eisenbichler-Markus#0","GER-M-Paschke-Pius#0","GER-M-Freund-Severin#0","ITA-M-Insam-Alex#0","JPN-M-Iwasa-Yuken#0","JPN-M-Sato-Keiichi#0","JPN-M-Kobayashi-Ryoyu#0","JPN-M-Nakamura-Naoki#0","JPN-M-Sato-Yukiya#0","JPN-M-Kobayashi-Junshiro#0","JPN-M-Tochimoto-Shohei#0","JPN-M-Takeuchi-Taku#0","JPN-M-Ito-Daiki#0","JPN-M-Kasai-Noriaki#0","KAZ-M-Tkachenko-Sergey#0","KOR-M-Choi-Seou#0","KOR-M-Choi-Heung_Chul#0","NOR-M-Markeng-Thomas_Aasen#0","NOR-M-Lindvik-Marius#0","NOR-M-Pedersen-Robin#0","NOR-M-Buskum-Andreas_Granerud#0","NOR-M-Granerud-Halvor_Egner#0","NOR-M-Forfang-Johann_Andre#0","NOR-M-Tande-Daniel_Andre#0","NOR-M-Aune-Joakim#0","NOR-M-Fannemel-Anders#0","NOR-M-Johansson-Robert#0","NOR-F-Lundby-Maren#0","NOR-F-Opseth-Silje#0","POL-M-Niznik-Adam#0","POL-M-Juroszek-Kacper#0","POL-M-Pilch-Tomasz#0","POL-M-Krzak-Jaroslaw#0","POL-M-Wasek-Pawel#0","POL-M-Stekala-Andrzej#0","POL-M-Wolny-Jakub#0","POL-M-Muranka-Klemens#0","POL-M-Zniszczol-Aleksander#0","POL-M-Kot-Maciej#0","POL-M-Kubacki-Dawid#0","POL-M-Stoch-Kamil#0","POL-M-Zyla-Piotr#0","POL-M-Hula-Stefan#0","RUS-M-Nazarov-Mikhail#0","RUS-M-Klimov-Evgeniy#0","RUS-M-Trofimov-Roman_Sergeevich#0","RUS-M-Vassiliev-Dmitriy#0","SLO-M-Mogel-Zak#0","SLO-M-Zajc-Timi#0","SLO-M-Prevc-Domen#0","SLO-M-Pavlovcic-Bor#0","SLO-M-Jelar-Ziga#0","SLO-M-Bartol-Tilen#0","SLO-M-Lanisek-Anze#0","SLO-M-Semenic-Anze#0","SLO-M-Prevc-Peter#0","SLO-M-Tepes-Jurij#0","SLO-M-Damjan-Jernej#0","SLO-F-Kriznar-Nika#0","SLO-F-Klinec-Ema#0","SUI-M-Peter-Dominik#0","SUI-M-Schuler-Andreas#0","SUI-M-Peier-Killian#0","SUI-M-Deschwanden-Gregor#0","SUI-M-Ammann-Simon#0","USA-M-Larson-Casey#0","USA-M-Bickner-Kevin#0"],"teams":[{"teamName":"Austria","countryCode":"AUT","competitorsIds":["AUT-M-Moerth-Claudio#0","AUT-M-Leitner-Clemens#0","AUT-M-Hoerl-Jan#0","AUT-M-Aschenwald-Philipp#0","AUT-M-Wohlgenannt-Ulrich#0","AUT-M-Huber-Stefan#0","AUT-M-Kraft-Stefan#0","AUT-M-Aigner-Clemens#0","AUT-M-Huber-Daniel#0","AUT-M-Schiffner-Markus#0","AUT-M-Hayboeck-Michael#0","AUT-M-Schlierenzauer-Gregor#0","AUT-M-Fettner-Manuel#0","AUT-F-Kramer-Marita#0","AUT-F-Hoelzl-Chiara#0","AUT-F-Sorschag-Sophie#0"]},{"teamName":"Bulgaria","countryCode":"BUL","competitorsIds":["BUL-M-Zografski-Vladimir#0"]},{"teamName":"Canada","countryCode":"CAN","competitorsIds":["CAN-M-Boyd-clowes-Mackenzie#0"]},{"teamName":"Czech Republic","countryCode":"CZE","competitorsIds":["CZE-M-Polasek-Viktor#0","CZE-M-Vancura-Tomas#0","CZE-M-Stursa-Vojtech#0","CZE-M-Kozisek-Cestmir#0","CZE-M-Koudelka-Roman#0","CZE-M-Hlava-Lukas#0"]},{"teamName":"Estonia","countryCode":"EST","competitorsIds":["EST-M-Aigro-Artti#0"]},{"teamName":"Finland","countryCode":"FIN","competitorsIds":["FIN-M-Kytosaho-Niko#0","FIN-M-Alamommo-Andreas#0","FIN-M-Nousiainen-Eetu#0","FIN-M-Aalto-Antti#0","FIN-M-Maatta-Jarkko#0"]},{"teamName":"France","countryCode":"FRA","competitorsIds":["FRA-M-Learoyd-Jonathan#0","FRA-F-Pagnier-Josephine#0"]},{"teamName":"Germany","countryCode":"GER","competitorsIds":["GER-M-Schmid-Constantin#0","GER-M-Baer-Moritz#0","GER-M-Siegel-David#0","GER-M-Wellinger-Andreas#0","GER-M-Geiger-Karl#0","GER-M-Leyhe-Stephan#0","GER-M-Freitag-Richard#0","GER-M-Eisenbichler-Markus#0","GER-M-Paschke-Pius#0","GER-M-Freund-Severin#0"]},{"teamName":"Italy","countryCode":"ITA","competitorsIds":["ITA-M-Insam-Alex#0"]},{"teamName":"Japan","countryCode":"JPN","competitorsIds":["JPN-M-Iwasa-Yuken#0","JPN-M-Sato-Keiichi#0","JPN-M-Kobayashi-Ryoyu#0","JPN-M-Nakamura-Naoki#0","JPN-M-Sato-Yukiya#0","JPN-M-Kobayashi-Junshiro#0","JPN-M-Tochimoto-Shohei#0","JPN-M-Takeuchi-Taku#0","JPN-M-Ito-Daiki#0","JPN-M-Kasai-Noriaki#0"]},{"teamName":"Kazakhstan","countryCode":"KAZ","competitorsIds":["KAZ-M-Tkachenko-Sergey#0"]},{"teamName":"Korea, Republic Of","countryCode":"KOR","competitorsIds":["KOR-M-Choi-Seou#0","KOR-M-Choi-Heung_Chul#0"]},{"teamName":"Norway","countryCode":"NOR","competitorsIds":["NOR-M-Markeng-Thomas_Aasen#0","NOR-M-Lindvik-Marius#0","NOR-M-Pedersen-Robin#0","NOR-M-Buskum-Andreas_Granerud#0","NOR-M-Granerud-Halvor_Egner#0","NOR-M-Forfang-Johann_Andre#0","NOR-M-Tande-Daniel_Andre#0","NOR-M-Aune-Joakim#0","NOR-M-Fannemel-Anders#0","NOR-M-Johansson-Robert#0","NOR-F-Lundby-Maren#0","NOR-F-Opseth-Silje#0"]},{"teamName":"Poland","countryCode":"POL","competitorsIds":["POL-M-Niznik-Adam#0","POL-M-Juroszek-Kacper#0","POL-M-Pilch-Tomasz#0","POL-M-Krzak-Jaroslaw#0","POL-M-Wasek-Pawel#0","POL-M-Stekala-Andrzej#0","POL-M-Wolny-Jakub#0","POL-M-Muranka-Klemens#0","POL-M-Zniszczol-Aleksander#0","POL-M-Kot-Maciej#0","POL-M-Kubacki-Dawid#0","POL-M-Stoch-Kamil#0","POL-M-Zyla-Piotr#0","POL-M-Hula-Stefan#0"]},{"teamName":"Russian Federation","countryCode":"RUS","competitorsIds":["RUS-M-Nazarov-Mikhail#0","RUS-M-Klimov-Evgeniy#0","RUS-M-Trofimov-Roman_Sergeevich#0","RUS-M-Vassiliev-Dmitriy#0"]},{"teamName":"Slovenia","countryCode":"SLO","competitorsIds":["SLO-M-Mogel-Zak#0","SLO-M-Zajc-Timi#0","SLO-M-Prevc-Domen#0","SLO-M-Pavlovcic-Bor#0","SLO-M-Jelar-Ziga#0","SLO-M-Bartol-Tilen#0","SLO-M-Lanisek-Anze#0","SLO-M-Semenic-Anze#0","SLO-M-Prevc-Peter#0","SLO-M-Tepes-Jurij#0","SLO-M-Damjan-Jernej#0","SLO-F-Kriznar-Nika#0","SLO-F-Klinec-Ema#0"]},{"teamName":"Switzerland","countryCode":"SUI","competitorsIds":["SUI-M-Peter-Dominik#0","SUI-M-Schuler-Andreas#0","SUI-M-Peier-Killian#0","SUI-M-Deschwanden-Gregor#0","SUI-M-Ammann-Simon#0"]},{"teamName":"United States","countryCode":"USA","competitorsIds":["USA-M-Larson-Casey#0","USA-M-Bickner-Kevin#0"]}],"classifications":[{"name":"World Cup","eventType":"Individual","classificationType":"Place","teamClassificationLimitType":0,"teamCompetitorsLimit":0,"medalPlaces":0,"events":[],"pointsTables":[{"name":"","value":[100,80,60,50,45,40,36,32,29,26,24,22,20,18,16,15,14,13,12,11,10,9,8,7,6,5,4,3,2,1]}],"leaderBibColor":"ffff00"},{"name":"Ski Flying World Cup","eventType":"Individual","classificationType":"Place","teamClassificationLimitType":0,"teamCompetitorsLimit":0,"medalPlaces":0,"events":[],"pointsTables":[{"name":"","value":[100,80,60,50,45,40,36,32,29,26,24,22,20,18,16,15,14,13,12,11,10,9,8,7,6,5,4,3,2,1]}],"leaderBibColor":"ffff00"},{"name":"Nations Cup","eventType":"Team","classificationType":"Place","teamClassificationLimitType":0,"teamCompetitorsLimit":0,"medalPlaces":0,"events":[],"pointsTables":[{"name":"","value":[100,80,60,50,45,40,36,32,29,26,24,22,20,18,16,15,14,13,12,11,10,9,8,7,6,5,4,3,2,1]},{"name":"","value":[400,350,300,250,200,150,100,50]}],"leaderBibColor":"ffff00"},{"name":"Four Hills Tournament","eventType":"Individual","classificationType":"Points","teamClassificationLimitType":0,"teamCompetitorsLimit":0,"medalPlaces":0,"events":[],"pointsTables":[],"leaderBibColor":"ffff00"}],"events":[{"classifications":[],"eventType":"Individual","hillId":"Wisla HS134","hillSurface":"Snow","id":0,"roundInfos":{"name":"Qualification","roundInfos":[{"roundType":"Normal","outLimitType":"Normal","outLimit":50,"useOrdRank":[false,false,false,false],"disableJudgesMarks":false,"has95Rule":true,"reversedBibs":false,"reassignBibs":false,"gateCompensation":true,"windCompensation":true}]},"ordRankType":"Classification","ordRankId":0,"qualRankType":"None","qualRankId":0,"inLimitType":"None","inLimit":0,"preQualRankType":"None","preQualRankId":0,"preQualLimitType":"None","preQualLimit":0},{"classifications":[0,2],"eventType":"Individual","hillId":"Wisla HS134","hillSurface":"Snow","id":1,"roundInfos":{"name":"Individual2Rounds","roundInfos":[{"roundType":"Normal","outLimitType":"Normal","outLimit":30,"useOrdRank":[false,false,false,false],"disableJudgesMarks":false,"has95Rule":true,"reversedBibs":false,"reassignBibs":false,"gateCompensation":true,"windCompensation":true},{"roundType":"Normal","outLimitType":"None","outLimit":-1,"useOrdRank":[false,false,false,false],"disableJudgesMarks":false,"has95Rule":true,"reversedBibs":false,"reassignBibs":false,"gateCompensation":true,"windCompensation":true}]},"ordRankType":"Classification","ordRankId":0,"qualRankType":"Event","qualRankId":0,"inLimitType":"None","inLimit":0,"preQualRankType":"None","preQualRankId":0,"preQualLimitType":"None","preQualLimit":0},{"classifications":[],"eventType":"Individual","hillId":"Kuusamo HS142","hillSurface":"Snow","id":2,"roundInfos":{"name":"Qualification","roundInfos":[{"roundType":"Normal","outLimitType":"Normal","outLimit":50,"useOrdRank":[false,false,false,false,false,false,false,false,false,false,false,false,false,false,false,false,false,false,false,false,false,false,false,false,false,false,false,false,false,false,false,false,false,false,false,false,false,false,false,false,false,false,false,false,false,false,false,false,false,false,false,false],"disableJudgesMarks":false,"has95Rule":true,"reversedBibs":false,"reassignBibs":false,"gateCompensation":true,"windCompensation":true}]},"ordRankType":"Classification","ordRankId":0,"qualRankType":"None","qualRankId":0,"inLimitType":"None","inLimit":0,"preQualRankType":"None","preQualRankId":0,"preQualLimitType":"None","preQualLimit":0},{"classifications":[0,2],"eventType":"Individual","hillId":"Kuusamo HS142","hillSurface":"Snow","id":3,"roundInfos":{"name":"Individual2Rounds","roundInfos":[{"roundType":"Normal","outLimitType":"Normal","outLimit":30,"useOrdRank":[false,false,false,false],"disableJudgesMarks":false,"has95Rule":true,"reversedBibs":false,"reassignBibs":false,"gateCompensation":true,"windCompensation":true},{"roundType":"Normal","outLimitType":"None","outLimit":-1,"useOrdRank":[false,false,false,false],"disableJudgesMarks":false,"has95Rule":true,"reversedBibs":false,"reassignBibs":false,"gateCompensation":true,"windCompensation":true}]},"ordRankType":"Classification","ordRankId":0,"qualRankType":"Event","qualRankId":3,"inLimitType":"None","inLimit":0,"preQualRankType":"None","preQualRankId":0,"preQualLimitType":"None","preQualLimit":0}]},{"name":"asd","competitorsIds":["AUT-M-Kraft-Stefan#0","NOR-M-Lindvik-Marius#0","POL-M-Hrynko-Jonatan#0"],"teams":[{"teamName":"Austria","countryCode":"AUT","competitorsIds":["AUT-M-Kraft-Stefan#0"]},{"teamName":"Norway","countryCode":"NOR","competitorsIds":["NOR-M-Lindvik-Marius#0"]},{"teamName":"Poland","countryCode":"POL","competitorsIds":["POL-M-Hrynko-Jonatan#0"]}],"classifications":[{"name":"WC","eventType":"Individual","classificationType":"Place","teamClassificationLimitType":0,"teamCompetitorsLimit":0,"medalPlaces":0,"events":[],"pointsTables":[{"name":"Individual","value":[100,80,60,50,45,40,36,32,29,26,24,22,20,18,16,15,14,13,12,11,10,9,8,7,6,5,4,3,2,1]}],"leaderBibColor":"ffff00"},{"name":"NC","eventType":"Team","classificationType":"Place","teamClassificationLimitType":0,"teamCompetitorsLimit":0,"medalPlaces":0,"events":[],"pointsTables":[{"name":"Individual","value":[100,80,60,50,45,40,36,32,29,26,24,22,20,18,16,15,14,13,12,11,10,9,8,7,6,5,4,3,2,1]},{"name":"Team","value":[400,350,300,250,200,150,100,50]}],"leaderBibColor":"ffaa00"}],"events":[{"classifications":[0,1],"eventType":"Individual","hillId":"Karpacz HS94","hillSurface":"Matting","id":0,"roundInfos":{"name":"Individual2Rounds","roundInfos":[{"roundType":"Normal","outLimitType":"Normal","outLimit":30,"useOrdRank":[false,false,false,false],"disableJudgesMarks":false,"has95Rule":true,"reversedBibs":false,"reassignBibs":false,"gateCompensation":true,"windCompensation":true},{"roundType":"Normal","outLimitType":"None","outLimit":-1,"useOrdRank":[false,false,false,false],"disableJudgesMarks":false,"has95Rule":true,"reversedBibs":false,"reassignBibs":false,"gateCompensation":true,"windCompensation":true}]},"ordRankType":"None","ordRankId":0,"qualRankType":"None","qualRankId":0,"inLimitType":"None","inLimit":0,"preQualRankType":"None","preQualRankId":0,"preQualLimitType":"None","preQualLimit":0},{"classifications":[0,1],"eventType":"Individual","hillId":"Almaty HS66","hillSurface":"Matting","id":1,"roundInfos":{"name":"Individual2Rounds","roundInfos":[{"roundType":"Normal","outLimitType":"Normal","outLimit":30,"useOrdRank":[false,false,false,false],"disableJudgesMarks":false,"has95Rule":true,"reversedBibs":false,"reassignBibs":false,"gateCompensation":true,"windCompensation":true},{"roundType":"Normal","outLimitType":"None","outLimit":-1,"useOrdRank":[false,false,false,false],"disableJudgesMarks":false,"has95Rule":true,"reversedBibs":false,"reassignBibs":false,"gateCompensation":true,"windCompensation":true}]},"ordRankType":"None","ordRankId":0,"qualRankType":"None","qualRankId":0,"inLimitType":"None","inLimit":0,"preQualRankType":"None","preQualRankId":0,"preQualLimitType":"None","preQualLimit":0}]},{"name":"Raw Air","competitorsIds":["NOR-M-Lindvik-Marius#0","NOR-M-Granerud-Halvor_Egner#0"],"teams":[{"teamName":"Norway","countryCode":"NOR","competitorsIds":["NOR-M-Lindvik-Marius#0","NOR-M-Granerud-Halvor_Egner#0"]}],"classifications":[{"name":"Raw Air","eventType":"Individual","classificationType":"Points","teamClassificationLimitType":0,"teamCompetitorsLimit":0,"medalPlaces":0,"events":[],"pointsTables":[{"name":"Individual","value":[100,80,60,50,45,40,36,32,29,26,24,22,20,18,16,15,14,13,12,11,10,9,8,7,6,5,4,3,2,1]}],"leaderBibColor":"6666aa"},{"name":"World Cup","eventType":"Individual","classificationType":"Place","teamClassificationLimitType":0,"teamCompetitorsLimit":0,"medalPlaces":0,"events":[],"pointsTables":[{"name":"Individual","value":[100,80,60,50,45,40,36,32,29,26,24,22,20,18,16,15,14,13,12,11,10,9,8,7,6,5,4,3,2,1]}],"leaderBibColor":"ffff00"},{"name":"Nations Cup","eventType":"Team","classificationType":"Place","teamClassificationLimitType":0,"teamCompetitorsLimit":0,"medalPlaces":0,"events":[],"pointsTables":[{"name":"Individual","value":[100,80,60,50,45,40,36,32,29,26,24,22,20,18,16,15,14,13,12,11,10,9,8,7,6,5,4,3,2,1]},{"name":"Team","value":[400,350,300,250,200,150,100,50]}],"leaderBibColor":"ffaa00"},{"name":"Xd","eventType":"Individual","classificationType":"Place","teamClassificationLimitType":0,"teamCompetitorsLimit":0,"medalPlaces":0,"events":[],"pointsTables":[{"name":"Worlc Cup","value":[100,80,60,50,45,40,36,32,29,26,24,22,20,18,16,15,14,13,12,11,10,9,8,7,6,5,4,3,2,1]}],"leaderBibColor":"ffff00"}],"events":[{"classifications":[1,2,0],"eventType":"Individual","hillId":"Oslo HS134","hillSurface":"Matting","id":0,"roundInfos":{"name":"Individual2Rounds5","roundInfos":[{"roundType":"Normal","outLimitType":"Normal","outLimit":5,"useOrdRank":[false,false,false,false],"disableJudgesMarks":false,"has95Rule":true,"reversedBibs":false,"reassignBibs":false,"gateCompensation":true,"windCompensation":true},{"roundType":"Normal","outLimitType":"None","outLimit":-1,"useOrdRank":[false,false,false,false],"disableJudgesMarks":false,"has95Rule":true,"reversedBibs":false,"reassignBibs":false,"gateCompensation":true,"windCompensation":true}]},"ordRankType":"None","ordRankId":0,"qualRankType":"None","qualRankId":0,"inLimitType":"None","inLimit":0,"preQualRankType":"None","preQualRankId":0,"preQualLimitType":"None","preQualLimit":0},{"classifications":[0],"eventType":"Individual","hillId":"Zakopane HS140","hillSurface":"Matting","id":1,"roundInfos":{"name":"Qualification8","roundInfos":[{"roundType":"Normal","outLimitType":"Normal","outLimit":8,"useOrdRank":[false,false,false,false],"disableJudgesMarks":false,"has95Rule":true,"reversedBibs":false,"reassignBibs":false,"gateCompensation":true,"windCompensation":true}]},"ordRankType":"Classification","ordRankId":1,"qualRankType":"None","qualRankId":0,"inLimitType":"None","inLimit":0,"preQualRankType":"None","preQualRankId":0,"preQualLimitType":"None","preQualLimit":0},{"classifications":[0,1,2],"eventType":"Individual","hillId":"Zakopane HS140","hillSurface":"Matting","id":2,"roundInfos":{"name":"Individual2Rounds5","roundInfos":[{"roundType":"Normal","outLimitType":"Normal","outLimit":5,"useOrdRank":[false,false,false,false],"disableJudgesMarks":false,"has95Rule":true,"reversedBibs":false,"reassignBibs":false,"gateCompensation":true,"windCompensation":true},{"roundType":"Normal","outLimitType":"None","outLimit":-1,"useOrdRank":[false,false,false,false],"disableJudgesMarks":false,"has95Rule":true,"reversedBibs":false,"reassignBibs":false,"gateCompensation":true,"windCompensation":true}]},"ordRankType":"Classification","ordRankId":1,"qualRankType":"Event","qualRankId":1,"inLimitType":"Normal","inLimit":8,"preQualRankType":"Classification","preQualRankId":1,"preQualLimitType":"Normal","preQualLimit":3}]},{"name":"Calendar","competitorsIds":["AUT-M-Moerth-Claudio#0","AUT-M-Leitner-Clemens#0","AUT-M-Hoerl-Jan#0","AUT-M-Aschenwald-Philipp#0","AUT-M-Wohlgenannt-Ulrich#0","AUT-M-Huber-Stefan#0","AUT-M-Kraft-Stefan#0","AUT-M-Aigner-Clemens#0","AUT-M-Huber-Daniel#0","AUT-M-Schiffner-Markus#0","AUT-M-Hayboeck-Michael#0","AUT-M-Schlierenzauer-Gregor#0","AUT-M-Fettner-Manuel#0","AUT-F-Kramer-Marita#0","BUL-M-Zografski-Vladimir#0","CAN-M-Boyd-clowes-Mackenzie#0","CZE-M-Polasek-Viktor#0","CZE-M-Vancura-Tomas#0","CZE-M-Stursa-Vojtech#0","CZE-M-Kozisek-Cestmir#0","CZE-M-Koudelka-Roman#0","CZE-M-Hlava-Lukas#0","EST-M-Aigro-Artti#0","FIN-M-Kytosaho-Niko#0","FIN-M-Alamommo-Andreas#0","FIN-M-Nousiainen-Eetu#0","FIN-M-Aalto-Antti#0","FIN-M-Maatta-Jarkko#0","FRA-M-Learoyd-Jonathan#0","GER-M-Schmid-Constantin#0","GER-M-Baer-Moritz#0","GER-M-Wellinger-Andreas#0","GER-M-Geiger-Karl#0","GER-M-Leyhe-Stephan#0","GER-M-Freitag-Richard#0","GER-M-Eisenbichler-Markus#0","GER-M-Paschke-Pius#0","GER-M-Freund-Severin#0","ITA-M-Insam-Alex#0","JPN-M-Iwasa-Yuken#0","JPN-M-Sato-Keiichi#0","JPN-M-Kobayashi-Ryoyu#0","JPN-M-Nakamura-Naoki#0","JPN-M-Sato-Yukiya#0","JPN-M-Kobayashi-Junshiro#0","JPN-M-Tochimoto-Shohei#0","JPN-M-Takeuchi-Taku#0","JPN-M-Ito-Daiki#0","JPN-M-Kasai-Noriaki#0","KAZ-M-Tkachenko-Sergey#0","KOR-M-Choi-Seou#0","KOR-M-Choi-Heung_Chul#0","NOR-M-Markeng-Thomas_Aasen#0","NOR-M-Lindvik-Marius#0","NOR-M-Pedersen-Robin#0","NOR-M-Buskum-Andreas_Granerud#0","NOR-M-Granerud-Halvor_Egner#0","NOR-M-Forfang-Johann_Andre#0","NOR-M-Tande-Daniel_Andre#0","NOR-M-Aune-Joakim#0","NOR-M-Fannemel-Anders#0","NOR-M-Johansson-Robert#0","NOR-F-Lundby-Maren#0","POL-M-Niznik-Adam#0","POL-M-Juroszek-Kacper#0","POL-M-Pilch-Tomasz#0","POL-M-Krzak-Jaroslaw#0","POL-M-Wasek-Pawel#0","POL-M-Stekala-Andrzej#0","POL-M-Wolny-Jakub#0","POL-M-Muranka-Klemens#0","POL-M-Zniszczol-Aleksander#0","POL-M-Kot-Maciej#0","POL-M-Kubacki-Dawid#0","POL-M-Stoch-Kamil#0","POL-M-Zyla-Piotr#0","POL-M-Hula-Stefan#0","RUS-M-Nazarov-Mikhail#0","RUS-M-Klimov-Evgeniy#0","RUS-M-Trofimov-Roman_Sergeevich#0","RUS-M-Vassiliev-Dmitriy#0","SLO-M-Mogel-Zak#0","SLO-M-Zajc-Timi#0","SLO-M-Prevc-Domen#0","SLO-M-Pavlovcic-Bor#0","SLO-M-Jelar-Ziga#0","SLO-M-Bartol-Tilen#0","SLO-M-Lanisek-Anze#0","SLO-M-Semenic-Anze#0","SLO-M-Prevc-Peter#0","SLO-M-Tepes-Jurij#0","SLO-M-Damjan-Jernej#0","SUI-M-Peter-Dominik#0","SUI-M-Schuler-Andreas#0","SUI-M-Peier-Killian#0","SUI-M-Deschwanden-Gregor#0","SUI-M-Ammann-Simon#0","USA-M-Larson-Casey#0","USA-M-Bickner-Kevin#0","AUT-F-Sorschag-Sophie#0","AUT-F-Hoelzl-Chiara#0"],"teams":[{"teamName":"Austria","countryCode":"AUT","competitorsIds":["AUT-M-Moerth-Claudio#0","AUT-M-Leitner-Clemens#0","AUT-M-Hoerl-Jan#0","AUT-M-Aschenwald-Philipp#0","AUT-M-Wohlgenannt-Ulrich#0","AUT-M-Huber-Stefan#0","AUT-M-Kraft-Stefan#0","AUT-M-Aigner-Clemens#0","AUT-M-Huber-Daniel#0","AUT-M-Schiffner-Markus#0","AUT-M-Hayboeck-Michael#0","AUT-M-Schlierenzauer-Gregor#0","AUT-M-Fettner-Manuel#0","AUT-F-Kramer-Marita#0","AUT-F-Sorschag-Sophie#0","AUT-F-Hoelzl-Chiara#0"]},{"teamName":"Bulgaria","countryCode":"BUL","competitorsIds":["BUL-M-Zografski-Vladimir#0"]},{"teamName":"Canada","countryCode":"CAN","competitorsIds":["CAN-M-Boyd-clowes-Mackenzie#0"]},{"teamName":"Czech Republic","countryCode":"CZE","competitorsIds":["CZE-M-Polasek-Viktor#0","CZE-M-Vancura-Tomas#0","CZE-M-Stursa-Vojtech#0","CZE-M-Kozisek-Cestmir#0","CZE-M-Koudelka-Roman#0","CZE-M-Hlava-Lukas#0"]},{"teamName":"Estonia","countryCode":"EST","competitorsIds":["EST-M-Aigro-Artti#0"]},{"teamName":"Finland","countryCode":"FIN","competitorsIds":["FIN-M-Kytosaho-Niko#0","FIN-M-Alamommo-Andreas#0","FIN-M-Nousiainen-Eetu#0","FIN-M-Aalto-Antti#0","FIN-M-Maatta-Jarkko#0"]},{"teamName":"France","countryCode":"FRA","competitorsIds":["FRA-M-Learoyd-Jonathan#0"]},{"teamName":"Germany","countryCode":"GER","competitorsIds":["GER-M-Schmid-Constantin#0","GER-M-Baer-Moritz#0","GER-M-Wellinger-Andreas#0","GER-M-Geiger-Karl#0","GER-M-Leyhe-Stephan#0","GER-M-Freitag-Richard#0","GER-M-Eisenbichler-Markus#0","GER-M-Paschke-Pius#0","GER-M-Freund-Severin#0"]},{"teamName":"Italy","countryCode":"ITA","competitorsIds":["ITA-M-Insam-Alex#0"]},{"teamName":"Japan","countryCode":"JPN","competitorsIds":["JPN-M-Iwasa-Yuken#0","JPN-M-Sato-Keiichi#0","JPN-M-Kobayashi-Ryoyu#0","JPN-M-Nakamura-Naoki#0","JPN-M-Sato-Yukiya#0","JPN-M-Kobayashi-Junshiro#0","JPN-M-Tochimoto-Shohei#0","JPN-M-Takeuchi-Taku#0","JPN-M-Ito-Daiki#0","JPN-M-Kasai-Noriaki#0"]},{"teamName":"Kazakhstan","countryCode":"KAZ","competitorsIds":["KAZ-M-Tkachenko-Sergey#0"]},{"teamName":"Korea, Republic Of","countryCode":"KOR","competitorsIds":["KOR-M-Choi-Seou#0","KOR-M-Choi-Heung_Chul#0"]},{"teamName":"Norway","countryCode":"NOR","competitorsIds":["NOR-M-Markeng-Thomas_Aasen#0","NOR-M-Lindvik-Marius#0","NOR-M-Pedersen-Robin#0","NOR-M-Buskum-Andreas_Granerud#0","NOR-M-Granerud-Halvor_Egner#0","NOR-M-Forfang-Johann_Andre#0","NOR-M-Tande-Daniel_Andre#0","NOR-M-Aune-Joakim#0","NOR-M-Fannemel-Anders#0","NOR-M-Johansson-Robert#0","NOR-F-Lundby-Maren#0"]},{"teamName":"Poland","countryCode":"POL","competitorsIds":["POL-M-Niznik-Adam#0","POL-M-Juroszek-Kacper#0","POL-M-Pilch-Tomasz#0","POL-M-Krzak-Jaroslaw#0","POL-M-Wasek-Pawel#0","POL-M-Stekala-Andrzej#0","POL-M-Wolny-Jakub#0","POL-M-Muranka-Klemens#0","POL-M-Zniszczol-Aleksander#0","POL-M-Kot-Maciej#0","POL-M-Kubacki-Dawid#0","POL-M-Stoch-Kamil#0","POL-M-Zyla-Piotr#0","POL-M-Hula-Stefan#0"]},{"teamName":"Russian Federation","countryCode":"RUS","competitorsIds":["RUS-M-Nazarov-Mikhail#0","RUS-M-Klimov-Evgeniy#0","RUS-M-Trofimov-Roman_Sergeevich#0","RUS-M-Vassiliev-Dmitriy#0"]},{"teamName":"Slovenia","countryCode":"SLO","competitorsIds":["SLO-M-Mogel-Zak#0","SLO-M-Zajc-Timi#0","SLO-M-Prevc-Domen#0","SLO-M-Pavlovcic-Bor#0","SLO-M-Jelar-Ziga#0","SLO-M-Bartol-Tilen#0","SLO-M-Lanisek-Anze#0","SLO-M-Semenic-Anze#0","SLO-M-Prevc-Peter#0","SLO-M-Tepes-Jurij#0","SLO-M-Damjan-Jernej#0"]},{"teamName":"Switzerland","countryCode":"SUI","competitorsIds":["SUI-M-Peter-Dominik#0","SUI-M-Schuler-Andreas#0","SUI-M-Peier-Killian#0","SUI-M-Deschwanden-Gregor#0","SUI-M-Ammann-Simon#0"]},{"teamName":"United States","countryCode":"USA","competitorsIds":["USA-M-Larson-Casey#0","USA-M-Bickner-Kevin#0"]}],"classifications":[{"name":"Tournament","eventType":"Individual","classificationType":"Points","teamClassificationLimitType":0,"teamCompetitorsLimit":0,"medalPlaces":0,"events":[],"pointsTables":[{"name":"Worlc Cup","value":[100,80,60,50,45,40,36,32,29,26,24,22,20,18,16,15,14,13,12,11,10,9,8,7,6,5,4,3,2,1]}],"leaderBibColor":"ffff00"}],"events":[{"classifications":[0],"eventType":"Individual","hillId":"Oberstdorf HS235","hillSurface":"Snow","id":0,"roundInfos":{"name":"Individual2Rounds","roundInfos":[{"roundType":"Normal","outLimitType":"Normal","outLimit":30,"useOrdRank":[false,false,false,false],"disableJudgesMarks":false,"has95Rule":true,"reversedBibs":false,"reassignBibs":false,"gateCompensation":true,"windCompensation":true},{"roundType":"Normal","outLimitType":"None","outLimit":-1,"useOrdRank":[false,false,false,false],"disableJudgesMarks":false,"has95Rule":true,"reversedBibs":false,"reassignBibs":false,"gateCompensation":true,"windCompensation":true}]},"ordRankType":"None","ordRankId":0,"qualRankType":"None","qualRankId":0,"inLimitType":"None","inLimit":0,"preQualRankType":"None","preQualRankId":0,"preQualLimitType":"None","preQualLimit":0}]},{"name":"Normal Hill","competitorsIds":["AUT-M-Moerth-Claudio#0","AUT-M-Leitner-Clemens#0","AUT-M-Hoerl-Jan#0","AUT-M-Aschenwald-Philipp#0","AUT-M-Wohlgenannt-Ulrich#0","AUT-M-Huber-Stefan#0","AUT-M-Kraft-Stefan#0","AUT-M-Aigner-Clemens#0","AUT-M-Huber-Daniel#0","AUT-M-Schiffner-Markus#0","AUT-M-Hayboeck-Michael#0","AUT-M-Schlierenzauer-Gregor#0","AUT-M-Fettner-Manuel#0","AUT-F-Kramer-Marita#0","BUL-M-Zografski-Vladimir#0","CAN-M-Boyd-clowes-Mackenzie#0","CZE-M-Polasek-Viktor#0","CZE-M-Vancura-Tomas#0","CZE-M-Stursa-Vojtech#0","CZE-M-Kozisek-Cestmir#0","CZE-M-Koudelka-Roman#0","CZE-M-Hlava-Lukas#0","EST-M-Aigro-Artti#0","FIN-M-Kytosaho-Niko#0","FIN-M-Alamommo-Andreas#0","FIN-M-Nousiainen-Eetu#0","FIN-M-Aalto-Antti#0","FIN-M-Maatta-Jarkko#0","FRA-M-Learoyd-Jonathan#0","GER-M-Schmid-Constantin#0","GER-M-Baer-Moritz#0","GER-M-Siegel-David#0","GER-M-Wellinger-Andreas#0","GER-M-Geiger-Karl#0","GER-M-Leyhe-Stephan#0","GER-M-Freitag-Richard#0","GER-M-Eisenbichler-Markus#0","GER-M-Paschke-Pius#0","GER-M-Freund-Severin#0","ITA-M-Insam-Alex#0","JPN-M-Iwasa-Yuken#0","JPN-M-Sato-Keiichi#0","JPN-M-Kobayashi-Ryoyu#0","JPN-M-Nakamura-Naoki#0","JPN-M-Sato-Yukiya#0","JPN-M-Kobayashi-Junshiro#0","JPN-M-Tochimoto-Shohei#0","JPN-M-Takeuchi-Taku#0","JPN-M-Ito-Daiki#0","JPN-M-Kasai-Noriaki#0","KAZ-M-Tkachenko-Sergey#0","KOR-M-Choi-Seou#0","KOR-M-Choi-Heung_Chul#0","NOR-M-Markeng-Thomas_Aasen#0","NOR-M-Lindvik-Marius#0","NOR-M-Pedersen-Robin#0","NOR-M-Buskum-Andreas_Granerud#0","NOR-M-Granerud-Halvor_Egner#0","NOR-M-Forfang-Johann_Andre#0","NOR-M-Tande-Daniel_Andre#0","NOR-M-Aune-Joakim#0","NOR-M-Fannemel-Anders#0","NOR-M-Johansson-Robert#0","NOR-F-Lundby-Maren#0","POL-M-Niznik-Adam#0","POL-M-Juroszek-Kacper#0","POL-M-Pilch-Tomasz#0","POL-M-Krzak-Jaroslaw#0","POL-M-Wasek-Pawel#0","POL-M-Stekala-Andrzej#0","POL-M-Wolny-Jakub#0","POL-M-Muranka-Klemens#0","POL-M-Zniszczol-Aleksander#0","POL-M-Kot-Maciej#0","POL-M-Kubacki-Dawid#0","POL-M-Stoch-Kamil#0","POL-M-Zyla-Piotr#0","POL-M-Hula-Stefan#0","RUS-M-Nazarov-Mikhail#0","RUS-M-Klimov-Evgeniy#0","RUS-M-Trofimov-Roman_Sergeevich#0","RUS-M-Vassiliev-Dmitriy#0","SLO-M-Mogel-Zak#0","SLO-M-Zajc-Timi#0","SLO-M-Prevc-Domen#0","SLO-M-Pavlovcic-Bor#0","SLO-M-Jelar-Ziga#0","SLO-M-Bartol-Tilen#0","SLO-M-Lanisek-Anze#0","SLO-M-Semenic-Anze#0","SLO-M-Prevc-Peter#0","SLO-M-Tepes-Jurij#0","SLO-M-Damjan-Jernej#0","SUI-M-Peter-Dominik#0","SUI-M-Schuler-Andreas#0","SUI-M-Peier-Killian#0","SUI-M-Deschwanden-Gregor#0","SUI-M-Ammann-Simon#0","USA-M-Larson-Casey#0","USA-M-Bickner-Kevin#0"],"teams":[{"teamName":"Austria","countryCode":"AUT","competitorsIds":["AUT-M-Moerth-Claudio#0","AUT-M-Leitner-Clemens#0","AUT-M-Hoerl-Jan#0","AUT-M-Aschenwald-Philipp#0","AUT-M-Wohlgenannt-Ulrich#0","AUT-M-Huber-Stefan#0","AUT-M-Kraft-Stefan#0","AUT-M-Aigner-Clemens#0","AUT-M-Huber-Daniel#0","AUT-M-Schiffner-Markus#0","AUT-M-Hayboeck-Michael#0","AUT-M-Schlierenzauer-Gregor#0","AUT-M-Fettner-Manuel#0","AUT-F-Kramer-Marita#0"]},{"teamName":"Bulgaria","countryCode":"BUL","competitorsIds":["BUL-M-Zografski-Vladimir#0"]},{"teamName":"Canada","countryCode":"CAN","competitorsIds":["CAN-M-Boyd-clowes-Mackenzie#0"]},{"teamName":"Czech Republic","countryCode":"CZE","competitorsIds":["CZE-M-Polasek-Viktor#0","CZE-M-Vancura-Tomas#0","CZE-M-Stursa-Vojtech#0","CZE-M-Kozisek-Cestmir#0","CZE-M-Koudelka-Roman#0","CZE-M-Hlava-Lukas#0"]},{"teamName":"Estonia","countryCode":"EST","competitorsIds":["EST-M-Aigro-Artti#0"]},{"teamName":"Finland","countryCode":"FIN","competitorsIds":["FIN-M-Kytosaho-Niko#0","FIN-M-Alamommo-Andreas#0","FIN-M-Nousiainen-Eetu#0","FIN-M-Aalto-Antti#0","FIN-M-Maatta-Jarkko#0"]},{"teamName":"France","countryCode":"FRA","competitorsIds":["FRA-M-Learoyd-Jonathan#0"]},{"teamName":"Germany","countryCode":"GER","competitorsIds":["GER-M-Schmid-Constantin#0","GER-M-Baer-Moritz#0","GER-M-Siegel-David#0","GER-M-Wellinger-Andreas#0","GER-M-Geiger-Karl#0","GER-M-Leyhe-Stephan#0","GER-M-Freitag-Richard#0","GER-M-Eisenbichler-Markus#0","GER-M-Paschke-Pius#0","GER-M-Freund-Severin#0"]},{"teamName":"Italy","countryCode":"ITA","competitorsIds":["ITA-M-Insam-Alex#0"]},{"teamName":"Japan","countryCode":"JPN","competitorsIds":["JPN-M-Iwasa-Yuken#0","JPN-M-Sato-Keiichi#0","JPN-M-Kobayashi-Ryoyu#0","JPN-M-Nakamura-Naoki#0","JPN-M-Sato-Yukiya#0","JPN-M-Kobayashi-Junshiro#0","JPN-M-Tochimoto-Shohei#0","JPN-M-Takeuchi-Taku#0","JPN-M-Ito-Daiki#0","JPN-M-Kasai-Noriaki#0"]},{"teamName":"Kazakhstan","countryCode":"KAZ","competitorsIds":["KAZ-M-Tkachenko-Sergey#0"]},{"teamName":"Korea, Republic Of","countryCode":"KOR","competitorsIds":["KOR-M-Choi-Seou#0","KOR-M-Choi-Heung_Chul#0"]},{"teamName":"Norway","countryCode":"NOR","competitorsIds":["NOR-M-Markeng-Thomas_Aasen#0","NOR-M-Lindvik-Marius#0","NOR-M-Pedersen-Robin#0","NOR-M-Buskum-Andreas_Granerud#0","NOR-M-Granerud-Halvor_Egner#0","NOR-M-Forfang-Johann_Andre#0","NOR-M-Tande-Daniel_Andre#0","NOR-M-Aune-Joakim#0","NOR-M-Fannemel-Anders#0","NOR-M-Johansson-Robert#0","NOR-F-Lundby-Maren#0"]},{"teamName":"Poland","countryCode":"POL","competitorsIds":["POL-M-Niznik-Adam#0","POL-M-Juroszek-Kacper#0","POL-M-Pilch-Tomasz#0","POL-M-Krzak-Jaroslaw#0","POL-M-Wasek-Pawel#0","POL-M-Stekala-Andrzej#0","POL-M-Wolny-Jakub#0","POL-M-Muranka-Klemens#0","POL-M-Zniszczol-Aleksander#0","POL-M-Kot-Maciej#0","POL-M-Kubacki-Dawid#0","POL-M-Stoch-Kamil#0","POL-M-Zyla-Piotr#0","POL-M-Hula-Stefan#0"]},{"teamName":"Russian Federation","countryCode":"RUS","competitorsIds":["RUS-M-Nazarov-Mikhail#0","RUS-M-Klimov-Evgeniy#0","RUS-M-Trofimov-Roman_Sergeevich#0","RUS-M-Vassiliev-Dmitriy#0"]},{"teamName":"Slovenia","countryCode":"SLO","competitorsIds":["SLO-M-Mogel-Zak#0","SLO-M-Zajc-Timi#0","SLO-M-Prevc-Domen#0","SLO-M-Pavlovcic-Bor#0","SLO-M-Jelar-Ziga#0","SLO-M-Bartol-Tilen#0","SLO-M-Lanisek-Anze#0","SLO-M-Semenic-Anze#0","SLO-M-Prevc-Peter#0","SLO-M-Tepes-Jurij#0","SLO-M-Damjan-Jernej#0"]},{"teamName":"Switzerland","countryCode":"SUI","competitorsIds":["SUI-M-Peter-Dominik#0","SUI-M-Schuler-Andreas#0","SUI-M-Peier-Killian#0","SUI-M-Deschwanden-Gregor#0","SUI-M-Ammann-Simon#0"]},{"teamName":"United States","countryCode":"USA","competitorsIds":["USA-M-Larson-Casey#0","USA-M-Bickner-Kevin#0"]}],"classifications":[{"name":"xddd","eventType":"Individual","classificationType":"Points","teamClassificationLimitType":0,"teamCompetitorsLimit":0,"medalPlaces":0,"events":[],"pointsTables":[{"name":"Worlc Cup","value":[100,80,60,50,45,40,36,32,29,26,24,22,20,18,16,15,14,13,12,11,10,9,8,7,6,5,4,3,2,1]}],"leaderBibColor":"ffff00"}],"events":[{"classifications":[],"eventType":"Individual","hillId":"Szczyrk HS104","hillSurface":"Snow","id":0,"roundInfos":{"name":"Individual2Rounds","roundInfos":[{"roundType":"Normal","outLimitType":"Normal","outLimit":30,"useOrdRank":[false,false,false,false],"disableJudgesMarks":false,"has95Rule":true,"reversedBibs":false,"reassignBibs":false,"gateCompensation":true,"windCompensation":true},{"roundType":"Normal","outLimitType":"None","outLimit":-1,"useOrdRank":[false,false,false,false],"disableJudgesMarks":false,"has95Rule":true,"reversedBibs":false,"reassignBibs":false,"gateCompensation":true,"windCompensation":true}]},"ordRankType":"None","ordRankId":0,"qualRankType":"None","qualRankId":0,"inLimitType":"None","inLimit":0,"preQualRankType":"None","preQualRankId":0,"preQualLimitType":"None","preQualLimit":0}]},{"name":"Large Hill","competitorsIds":["AUT-M-Moerth-Claudio#0","AUT-M-Leitner-Clemens#0","AUT-M-Hoerl-Jan#0","AUT-M-Aschenwald-Philipp#0","AUT-M-Wohlgenannt-Ulrich#0","AUT-M-Huber-Stefan#0","AUT-M-Kraft-Stefan#0","AUT-M-Aigner-Clemens#0","AUT-M-Huber-Daniel#0","AUT-M-Schiffner-Markus#0","AUT-M-Hayboeck-Michael#0","AUT-M-Schlierenzauer-Gregor#0","AUT-M-Fettner-Manuel#0","AUT-F-Kramer-Marita#0","BUL-M-Zografski-Vladimir#0","CAN-M-Boyd-clowes-Mackenzie#0","CZE-M-Polasek-Viktor#0","CZE-M-Vancura-Tomas#0","CZE-M-Stursa-Vojtech#0","CZE-M-Kozisek-Cestmir#0","CZE-M-Koudelka-Roman#0","CZE-M-Hlava-Lukas#0","EST-M-Aigro-Artti#0","FIN-M-Kytosaho-Niko#0","FIN-M-Alamommo-Andreas#0","FIN-M-Nousiainen-Eetu#0","FIN-M-Aalto-Antti#0","FIN-M-Maatta-Jarkko#0","FRA-M-Learoyd-Jonathan#0","GER-M-Schmid-Constantin#0","GER-M-Baer-Moritz#0","GER-M-Wellinger-Andreas#0","GER-M-Geiger-Karl#0","GER-M-Leyhe-Stephan#0","GER-M-Freitag-Richard#0","GER-M-Eisenbichler-Markus#0","GER-M-Paschke-Pius#0","GER-M-Freund-Severin#0","ITA-M-Insam-Alex#0","JPN-M-Iwasa-Yuken#0","JPN-M-Sato-Keiichi#0","JPN-M-Kobayashi-Ryoyu#0","JPN-M-Nakamura-Naoki#0","JPN-M-Sato-Yukiya#0","JPN-M-Kobayashi-Junshiro#0","JPN-M-Tochimoto-Shohei#0","JPN-M-Takeuchi-Taku#0","JPN-M-Ito-Daiki#0","JPN-M-Kasai-Noriaki#0","KAZ-M-Tkachenko-Sergey#0","KOR-M-Choi-Seou#0","KOR-M-Choi-Heung_Chul#0","NOR-M-Markeng-Thomas_Aasen#0","NOR-M-Lindvik-Marius#0","NOR-M-Pedersen-Robin#0","NOR-M-Buskum-Andreas_Granerud#0","NOR-M-Granerud-Halvor_Egner#0","NOR-M-Forfang-Johann_Andre#0","NOR-M-Tande-Daniel_Andre#0","NOR-M-Aune-Joakim#0","NOR-M-Fannemel-Anders#0","NOR-M-Johansson-Robert#0","NOR-F-Lundby-Maren#0","POL-M-Niznik-Adam#0","POL-M-Juroszek-Kacper#0","POL-M-Pilch-Tomasz#0","POL-M-Krzak-Jaroslaw#0","POL-M-Wasek-Pawel#0","POL-M-Stekala-Andrzej#0","POL-M-Wolny-Jakub#0","POL-M-Muranka-Klemens#0","POL-M-Zniszczol-Aleksander#0","POL-M-Kot-Maciej#0","POL-M-Kubacki-Dawid#0","POL-M-Stoch-Kamil#0","POL-M-Zyla-Piotr#0","POL-M-Hula-Stefan#0","RUS-M-Nazarov-Mikhail#0","RUS-M-Klimov-Evgeniy#0","RUS-M-Trofimov-Roman_Sergeevich#0","RUS-M-Vassiliev-Dmitriy#0","SLO-M-Mogel-Zak#0","SLO-M-Zajc-Timi#0","SLO-M-Prevc-Domen#0","SLO-M-Pavlovcic-Bor#0","SLO-M-Jelar-Ziga#0","SLO-M-Bartol-Tilen#0","SLO-M-Lanisek-Anze#0","SLO-M-Semenic-Anze#0","SLO-M-Prevc-Peter#0","SLO-M-Tepes-Jurij#0","SLO-M-Damjan-Jernej#0","SUI-M-Peter-Dominik#0","SUI-M-Schuler-Andreas#0","SUI-M-Peier-Killian#0","SUI-M-Deschwanden-Gregor#0","SUI-M-Ammann-Simon#0","USA-M-Larson-Casey#0","USA-M-Bickner-Kevin#0"],"teams":[{"teamName":"Austria","countryCode":"AUT","competitorsIds":["AUT-M-Moerth-Claudio#0","AUT-M-Leitner-Clemens#0","AUT-M-Hoerl-Jan#0","AUT-M-Aschenwald-Philipp#0","AUT-M-Wohlgenannt-Ulrich#0","AUT-M-Huber-Stefan#0","AUT-M-Kraft-Stefan#0","AUT-M-Aigner-Clemens#0","AUT-M-Huber-Daniel#0","AUT-M-Schiffner-Markus#0","AUT-M-Hayboeck-Michael#0","AUT-M-Schlierenzauer-Gregor#0","AUT-M-Fettner-Manuel#0","AUT-F-Kramer-Marita#0"]},{"teamName":"Bulgaria","countryCode":"BUL","competitorsIds":["BUL-M-Zografski-Vladimir#0"]},{"teamName":"Canada","countryCode":"CAN","competitorsIds":["CAN-M-Boyd-clowes-Mackenzie#0"]},{"teamName":"Czech Republic","countryCode":"CZE","competitorsIds":["CZE-M-Polasek-Viktor#0","CZE-M-Vancura-Tomas#0","CZE-M-Stursa-Vojtech#0","CZE-M-Kozisek-Cestmir#0","CZE-M-Koudelka-Roman#0","CZE-M-Hlava-Lukas#0"]},{"teamName":"Estonia","countryCode":"EST","competitorsIds":["EST-M-Aigro-Artti#0"]},{"teamName":"Finland","countryCode":"FIN","competitorsIds":["FIN-M-Kytosaho-Niko#0","FIN-M-Alamommo-Andreas#0","FIN-M-Nousiainen-Eetu#0","FIN-M-Aalto-Antti#0","FIN-M-Maatta-Jarkko#0"]},{"teamName":"France","countryCode":"FRA","competitorsIds":["FRA-M-Learoyd-Jonathan#0"]},{"teamName":"Germany","countryCode":"GER","competitorsIds":["GER-M-Schmid-Constantin#0","GER-M-Baer-Moritz#0","GER-M-Wellinger-Andreas#0","GER-M-Geiger-Karl#0","GER-M-Leyhe-Stephan#0","GER-M-Freitag-Richard#0","GER-M-Eisenbichler-Markus#0","GER-M-Paschke-Pius#0","GER-M-Freund-Severin#0"]},{"teamName":"Italy","countryCode":"ITA","competitorsIds":["ITA-M-Insam-Alex#0"]},{"teamName":"Japan","countryCode":"JPN","competitorsIds":["JPN-M-Iwasa-Yuken#0","JPN-M-Sato-Keiichi#0","JPN-M-Kobayashi-Ryoyu#0","JPN-M-Nakamura-Naoki#0","JPN-M-Sato-Yukiya#0","JPN-M-Kobayashi-Junshiro#0","JPN-M-Tochimoto-Shohei#0","JPN-M-Takeuchi-Taku#0","JPN-M-Ito-Daiki#0","JPN-M-Kasai-Noriaki#0"]},{"teamName":"Kazakhstan","countryCode":"KAZ","competitorsIds":["KAZ-M-Tkachenko-Sergey#0"]},{"teamName":"Korea, Republic Of","countryCode":"KOR","competitorsIds":["KOR-M-Choi-Seou#0","KOR-M-Choi-Heung_Chul#0"]},{"teamName":"Norway","countryCode":"NOR","competitorsIds":["NOR-M-Markeng-Thomas_Aasen#0","NOR-M-Lindvik-Marius#0","NOR-M-Pedersen-Robin#0","NOR-M-Buskum-Andreas_Granerud#0","NOR-M-Granerud-Halvor_Egner#0","NOR-M-Forfang-Johann_Andre#0","NOR-M-Tande-Daniel_Andre#0","NOR-M-Aune-Joakim#0","NOR-M-Fannemel-Anders#0","NOR-M-Johansson-Robert#0","NOR-F-Lundby-Maren#0"]},{"teamName":"Poland","countryCode":"POL","competitorsIds":["POL-M-Niznik-Adam#0","POL-M-Juroszek-Kacper#0","POL-M-Pilch-Tomasz#0","POL-M-Krzak-Jaroslaw#0","POL-M-Wasek-Pawel#0","POL-M-Stekala-Andrzej#0","POL-M-Wolny-Jakub#0","POL-M-Muranka-Klemens#0","POL-M-Zniszczol-Aleksander#0","POL-M-Kot-Maciej#0","POL-M-Kubacki-Dawid#0","POL-M-Stoch-Kamil#0","POL-M-Zyla-Piotr#0","POL-M-Hula-Stefan#0"]},{"teamName":"Russian Federation","countryCode":"RUS","competitorsIds":["RUS-M-Nazarov-Mikhail#0","RUS-M-Klimov-Evgeniy#0","RUS-M-Trofimov-Roman_Sergeevich#0","RUS-M-Vassiliev-Dmitriy#0"]},{"teamName":"Slovenia","countryCode":"SLO","competitorsIds":["SLO-M-Mogel-Zak#0","SLO-M-Zajc-Timi#0","SLO-M-Prevc-Domen#0","SLO-M-Pavlovcic-Bor#0","SLO-M-Jelar-Ziga#0","SLO-M-Bartol-Tilen#0","SLO-M-Lanisek-Anze#0","SLO-M-Semenic-Anze#0","SLO-M-Prevc-Peter#0","SLO-M-Tepes-Jurij#0","SLO-M-Damjan-Jernej#0"]},{"teamName":"Switzerland","countryCode":"SUI","competitorsIds":["SUI-M-Peter-Dominik#0","SUI-M-Schuler-Andreas#0","SUI-M-Peier-Killian#0","SUI-M-Deschwanden-Gregor#0","SUI-M-Ammann-Simon#0"]},{"teamName":"United States","countryCode":"USA","competitorsIds":["USA-M-Larson-Casey#0","USA-M-Bickner-Kevin#0"]}],"classifications":[{"name":"asdf","eventType":"Individual","classificationType":"Place","teamClassificationLimitType":0,"teamCompetitorsLimit":0,"medalPlaces":0,"events":[],"pointsTables":[{"name":"Worlc Cup","value":[100,80,60,50,45,40,36,32,29,26,24,22,20,18,16,15,14,13,12,11,10,9,8,7,6,5,4,3,2,1]}],"leaderBibColor":"ffff00"}],"events":[{"classifications":[0],"eventType":"Individual","hillId":"Nizhny Tagil HS134","hillSurface":"Matting","id":0,"roundInfos":{"name":"Individual2Rounds","roundInfos":[{"roundType":"Normal","outLimitType":"Normal","outLimit":30,"useOrdRank":[false,false,false,false],"disableJudgesMarks":false,"has95Rule":true,"reversedBibs":false,"reassignBibs":false,"gateCompensation":true,"windCompensation":true},{"roundType":"Normal","outLimitType":"None","outLimit":-1,"useOrdRank":[false,false,false,false],"disableJudgesMarks":false,"has95Rule":true,"reversedBibs":false,"reassignBibs":false,"gateCompensation":true,"windCompensation":true}]},"ordRankType":"None","ordRankId":0,"qualRankType":"None","qualRankId":0,"inLimitType":"None","inLimit":0,"preQualRankType":"None","preQualRankId":0,"preQualLimitType":"None","preQualLimit":0}]},{"name":"Ko test","competitorsIds":["AUT-M-Moerth-Claudio#0","AUT-M-Leitner-Clemens#0","AUT-M-Hoerl-Jan#0","AUT-M-Aschenwald-Philipp#0","AUT-M-Wohlgenannt-Ulrich#0","AUT-M-Huber-Stefan#0"],"teams":[{"teamName":"Austria","countryCode":"AUT","competitorsIds":["AUT-M-Moerth-Claudio#0","AUT-M-Leitner-Clemens#0","AUT-M-Hoerl-Jan#0","AUT-M-Aschenwald-Philipp#0","AUT-M-Wohlgenannt-Ulrich#0","AUT-M-Huber-Stefan#0"]}],"classifications":[{"name":"World Cup","eventType":"Individual","classificationType":"Place","teamClassificationLimitType":0,"teamCompetitorsLimit":0,"medalPlaces":0,"events":[],"pointsTables":[{"name":"World Cup","value":[100,80,60,50,45,40,36,32,29,26,24,22,20,18,16,15,14,13,12,11,10,9,8,7,6,5,4,3,2,1]}],"leaderBibColor":"ffff00"},{"name":"Four Hills Tournament","eventType":"Individual","classificationType":"Points","teamClassificationLimitType":0,"teamCompetitorsLimit":0,"medalPlaces":0,"events":[],"pointsTables":[{"name":"World Cup","value":[100,80,60,50,45,40,36,32,29,26,24,22,20,18,16,15,14,13,12,11,10,9,8,7,6,5,4,3,2,1]}],"leaderBibColor":"77ccaa"}],"events":[{"classifications":[0],"eventType":"Individual","hillId":"Engelberg HS140","hillSurface":"Snow","id":0,"roundInfos":{"name":"Individual2Rounds","roundInfos":[{"roundType":"Normal","outLimitType":"Normal","outLimit":30,"useOrdRank":[false,false,false,false],"disableJudgesMarks":false,"has95Rule":true,"reversedBibs":false,"reassignBibs":false,"gateCompensation":true,"windCompensation":true},{"roundType":"Normal","outLimitType":"None","outLimit":-1,"useOrdRank":[false,false,false,false],"disableJudgesMarks":false,"has95Rule":true,"reversedBibs":false,"reassignBibs":false,"gateCompensation":true,"windCompensation":true}]},"ordRankType":"None","ordRankId":0,"qualRankType":"None","qualRankId":0,"inLimitType":"None","inLimit":0,"preQualRankType":"None","preQualRankId":0,"preQualLimitType":"None","preQualLimit":0},{"classifications":[],"eventType":"Individual","hillId":"Oberstdorf HS137","hillSurface":"Snow","id":1,"roundInfos":{"name":"QualificationKO","roundInfos":[{"roundType":"Normal","outLimitType":"Exact","outLimit":50,"useOrdRank":[false,false,false,false],"disableJudgesMarks":false,"has95Rule":true,"reversedBibs":false,"reassignBibs":false,"gateCompensation":true,"windCompensation":true}]},"ordRankType":"Classification","ordRankId":0,"qualRankType":"None","qualRankId":0,"inLimitType":"None","inLimit":0,"preQualRankType":"None","preQualRankId":0,"preQualLimitType":"None","preQualLimit":0},{"classifications":[1,0],"eventType":"Individual","hillId":"Oberstdorf HS137","hillSurface":"Snow","id":2,"roundInfos":{"name":"IndividualKO15","roundInfos":[{"roundType":"KO","outLimitType":"Normal","outLimit":15,"useOrdRank":[false,false,false,false],"disableJudgesMarks":false,"has95Rule":true,"reversedBibs":true,"reassignBibs":false,"gateCompensation":true,"windCompensation":true},{"roundType":"Normal","outLimitType":"None","outLimit":-1,"useOrdRank":[false,false,false,false],"disableJudgesMarks":false,"has95Rule":true,"reversedBibs":true,"reassignBibs":false,"gateCompensation":true,"windCompensation":true}]},"ordRankType":"Event","ordRankId":1,"qualRankType":"Event","qualRankId":1,"inLimitType":"None","inLimit":0,"preQualRankType":"None","preQualRankId":0,"preQualLimitType":"None","preQualLimit":0},{"classifications":[],"eventType":"Individual","hillId":"Garmisch-Partenkirchen HS142","hillSurface":"Snow","id":3,"roundInfos":{"name":"QualificationKO","roundInfos":[{"roundType":"Normal","outLimitType":"Exact","outLimit":50,"useOrdRank":[false,false,false,false],"disableJudgesMarks":false,"has95Rule":true,"reversedBibs":false,"reassignBibs":false,"gateCompensation":true,"windCompensation":true}]},"ordRankType":"Classification","ordRankId":0,"qualRankType":"None","qualRankId":0,"inLimitType":"None","inLimit":0,"preQualRankType":"None","preQualRankId":0,"preQualLimitType":"None","preQualLimit":0},{"classifications":[1,0],"eventType":"Individual","hillId":"Garmisch-Partenkirchen HS142","hillSurface":"Snow","id":4,"roundInfos":{"name":"IndividualKO15","roundInfos":[{"roundType":"KO","outLimitType":"Normal","outLimit":15,"useOrdRank":[false,false,false,false],"disableJudgesMarks":false,"has95Rule":true,"reversedBibs":true,"reassignBibs":false,"gateCompensation":true,"windCompensation":true},{"roundType":"Normal","outLimitType":"None","outLimit":-1,"useOrdRank":[false,false,false,false],"disableJudgesMarks":false,"has95Rule":true,"reversedBibs":true,"reassignBibs":false,"gateCompensation":true,"windCompensation":true}]},"ordRankType":"Event","ordRankId":1,"qualRankType":"Event","qualRankId":3,"inLimitType":"None","inLimit":0,"preQualRankType":"None","preQualRankId":0,"preQualLimitType":"None","preQualLimit":0}]}]